{
    "graphics": {
        "vertex_layout": [],
        "parameter": {
            "ash_object": {
                "type": "buffer"
            },
            "ash_pass": {
                "type": "buffer"
            }
        },
        "parameter_layout": [],
        "pipeline": [],
        "technique": [],
        "plugin": "ash-graphics-d3d12.dll",
        "render_concurrency": 4,
        "frame_resource": 3
    },
    "window": {
        "title": "ash app",
        "width": 700,
        "height": 400
    },
    "core": {
        "threads": 0
    }
}